passwordtools/__init__.py
passwordtools/passwordtools.py
passwordtools-0.0.6.dist-info/LICENSE
passwordtools-0.0.6.dist-info/METADATA
passwordtools-0.0.6.dist-info/WHEEL
passwordtools-0.0.6.dist-info/top_level.txt
passwordtools-0.0.6.dist-info/RECORD
